mailcomposer/__init__.py
mailcomposer/__main__.py
mailcomposer/base.py
mailcomposer/dummy.py
mailcomposer/exceptions.py
mailcomposer/outlook.py
mailcomposer/thunderbird.py
mailcomposer/util.py
mailcomposer/xdg_email.py
mailcomposer-0.2.4.dist-info/LICENSE
mailcomposer-0.2.4.dist-info/METADATA
mailcomposer-0.2.4.dist-info/WHEEL
mailcomposer-0.2.4.dist-info/top_level.txt
mailcomposer-0.2.4.dist-info/RECORD
