Metadata-Version: 2.1
Name: mailcomposer
Version: 0.2.4
Summary: API for composing emails through an external application
Home-page: https://github.com/bmjcode/mailcomposer
Author: Benjamin Johnson
Author-email: bmjcode@gmail.com
License: UNKNOWN
Platform: UNKNOWN
Classifier: Development Status :: 4 - Beta
Classifier: Programming Language :: Python :: 2
Classifier: Programming Language :: Python :: 3
Classifier: License :: OSI Approved :: MIT License
Classifier: Operating System :: OS Independent
